genpnize/__init__.py
genpnize/__main__.py
genpnize/iter_recipes.py
genpnize/producer.py
genpnize-0.1.0.dist-info/LICENSE
genpnize-0.1.0.dist-info/METADATA
genpnize-0.1.0.dist-info/WHEEL
genpnize-0.1.0.dist-info/entry_points.txt
genpnize-0.1.0.dist-info/top_level.txt
genpnize-0.1.0.dist-info/RECORD
